LICENSE
MANIFEST.in
README.md
requirements.txt
setup.py
tox.ini
ckeditor/__init__.py
ckeditor/forms.py
ckeditor/models.py
ckeditor/urls.py
ckeditor/views.py
ckeditor/static/javascript/ckeditor-config.js
ckeditor/static/javascript/ckeditor/CHANGES.md
ckeditor/static/javascript/ckeditor/LICENSE.md
ckeditor/static/javascript/ckeditor/README.md
ckeditor/static/javascript/ckeditor/build-config.js
ckeditor/static/javascript/ckeditor/ckeditor.js
ckeditor/static/javascript/ckeditor/config.js
ckeditor/static/javascript/ckeditor/contents.css
ckeditor/static/javascript/ckeditor/styles.js
ckeditor/static/javascript/ckeditor/adapters/jquery.js
ckeditor/static/javascript/ckeditor/lang/af.js
ckeditor/static/javascript/ckeditor/lang/ar.js
ckeditor/static/javascript/ckeditor/lang/bg.js
ckeditor/static/javascript/ckeditor/lang/bn.js
ckeditor/static/javascript/ckeditor/lang/bs.js
ckeditor/static/javascript/ckeditor/lang/ca.js
ckeditor/static/javascript/ckeditor/lang/cs.js
ckeditor/static/javascript/ckeditor/lang/cy.js
ckeditor/static/javascript/ckeditor/lang/da.js
ckeditor/static/javascript/ckeditor/lang/de.js
ckeditor/static/javascript/ckeditor/lang/el.js
ckeditor/static/javascript/ckeditor/lang/en-au.js
ckeditor/static/javascript/ckeditor/lang/en-ca.js
ckeditor/static/javascript/ckeditor/lang/en-gb.js
ckeditor/static/javascript/ckeditor/lang/en.js
ckeditor/static/javascript/ckeditor/lang/eo.js
ckeditor/static/javascript/ckeditor/lang/es.js
ckeditor/static/javascript/ckeditor/lang/et.js
ckeditor/static/javascript/ckeditor/lang/eu.js
ckeditor/static/javascript/ckeditor/lang/fa.js
ckeditor/static/javascript/ckeditor/lang/fi.js
ckeditor/static/javascript/ckeditor/lang/fo.js
ckeditor/static/javascript/ckeditor/lang/fr-ca.js
ckeditor/static/javascript/ckeditor/lang/fr.js
ckeditor/static/javascript/ckeditor/lang/gl.js
ckeditor/static/javascript/ckeditor/lang/gu.js
ckeditor/static/javascript/ckeditor/lang/he.js
ckeditor/static/javascript/ckeditor/lang/hi.js
django_ckedit.egg-info/PKG-INFO
django_ckedit.egg-info/SOURCES.txt
django_ckedit.egg-info/dependency_links.txt
django_ckedit.egg-info/requires.txt
django_ckedit.egg-info/top_level.txt