Metadata-Version: 1.1
Name: django-ckedit
Version: 1.0
Summary: Django integration with the popular WYSIWYG editor CKEditor.
Home-page: https://bitbucket.org/nextscreenlabs/django-ckeditor
Author: Jason Christa
Author-email: jason@zeitcode.com
License: UNKNOWN
Platform: UNKNOWN
Classifier: Environment :: Web Environment
Classifier: License :: OSI Approved :: BSD License
Classifier: Framework :: Django
Classifier: Programming Language :: Python
